keyczar/__init__.py
keyczar/errors.py
keyczar/keyczar.py
keyczar/keyczart.py
keyczar/keydata.py
keyczar/keyinfo.py
keyczar/keys.py
keyczar/readers.py
keyczar/util.py
keyczar/writers.py
python_keyczar_2-0.725.dist-info/LICENSE
python_keyczar_2-0.725.dist-info/METADATA
python_keyczar_2-0.725.dist-info/WHEEL
python_keyczar_2-0.725.dist-info/entry_points.txt
python_keyczar_2-0.725.dist-info/top_level.txt
python_keyczar_2-0.725.dist-info/RECORD
