Metadata-Version: 2.1
Name: python-keyczar-2
Version: 0.725
Summary: Toolkit for safe and simple cryptography
Home-page: http://www.keyczar.org/
Author: Arkajit Dey
Author-email: arkajit.dey@gmail.com
Maintainer: Google, Inc.
Maintainer-email: keyczar-discuss@googlegroups.com
License: http://www.apache.org/licenses/LICENSE-2.0
Platform: any
Classifier: Development Status :: 5 - Production/Stable
Classifier: Intended Audience :: Developers
Classifier: License :: OSI Approved :: Apache Software License
Classifier: Programming Language :: Python
Classifier: Topic :: Security
Classifier: Topic :: Security :: Cryptography
Classifier: Topic :: Software Development :: Libraries :: Python Modules
Classifier: Operating System :: MacOS :: MacOS X
Classifier: Operating System :: Microsoft :: Windows
Classifier: Operating System :: Unix
License-File: LICENSE
Requires-Dist: pycryptodome (>3.0)
Requires-Dist: pyasn1
